setup.py
client/__init__.py
client/client.py
client/client/__init__.py
client/client/add_contact.py
client/client/client_database.py
client/client/client_transport.py
client/client/del_contact.py
client/client/main_window.py
client/client/main_window_conv.py
client/client/start_dialog.py
client/common/__init__.py
client/common/decos.py
client/common/descriptors.py
client/common/errors.py
client/common/metaclasses.py
client/common/settings.py
client/common/utils.py
client/log/__init__.py
client/log/client_log_config.py
client/log/server_log_config.py
client/unit_tests/__init__.py
client/unit_tests/test_client.py
client/unit_tests/test_server.py
client/unit_tests/test_utils.py
msg_client_gb.egg-info/PKG-INFO
msg_client_gb.egg-info/SOURCES.txt
msg_client_gb.egg-info/dependency_links.txt
msg_client_gb.egg-info/requires.txt
msg_client_gb.egg-info/top_level.txt